southwind/__init__.py
southwind/main.py
southwind-0.1.0.dist-info/LICENSE
southwind-0.1.0.dist-info/METADATA
southwind-0.1.0.dist-info/WHEEL
southwind-0.1.0.dist-info/top_level.txt
southwind-0.1.0.dist-info/RECORD
