Metadata-Version: 2.1
Name: southwind
Version: 0.1.0
Summary: A foundational Python package, reserving the 'southwind' namespace for future development and advanced features.
Author-email: Edoardo Spada <edoardo@southwind.ai>
License: Copyright (c) 2018 The Python Packaging Authority
Classifier: Programming Language :: Python :: 3
Classifier: License :: OSI Approved :: MIT License
Classifier: Operating System :: OS Independent
Requires-Python: >=3.8
License-File: LICENSE
